[{"id":2927003001,"name":"Singaram","level":3,"Mandal":2927003000,"District":2927000000,"State":2900000000,"GEOJSON":[]},{"id":2927003002,"name":"Jala","level":3,"Mandal":2927003000,"District":2927000000,"State":2900000000,"GEOJSON":[]},{"id":2927003003,"name":"Kurraram","level":3,"Mandal":2927003000,"District":2927000000,"State":2900000000,"GEOJSON":[]},{"id":2927003004,"name":"Burugu Palle","level":3,"Mandal":2927003000,"District":2927000000,"State":2900000000,"GEOJSON":[]},{"id":2927003005,"name":"Paru Palle","level":3,"Mandal":2927003000,"District":2927000000,"State":2900000000,"GEOJSON":[]},{"id":2927003006,"name":"Bondugula","level":3,"Mandal":2927003000,"District":2927000000,"State":2900000000,"GEOJSON":[]},{"id":2927003007,"name":"Somaram","level":3,"Mandal":2927003000,"District":2927000000,"State":2900000000,"GEOJSON":[]},{"id":2927003008,"name":"Nemila","level":3,"Mandal":2927003000,"District":2927000000,"State":2900000000,"GEOJSON":[]},{"id":2927003009,"name":"Rajapet","level":3,"Mandal":2927003000,"District":2927000000,"State":2900000000,"GEOJSON":[]},{"id":2927003010,"name":"Pamukunta","level":3,"Mandal":2927003000,"District":2927000000,"State":2900000000,"GEOJSON":[]},{"id":2927003011,"name":"Narsapuram","level":3,"Mandal":2927003000,"District":2927000000,"State":2900000000,"GEOJSON":[]},{"id":2927003012,"name":"Renikunta","level":3,"Mandal":2927003000,"District":2927000000,"State":2900000000,"GEOJSON":[]},{"id":2927003013,"name":"Basanthapuram","level":3,"Mandal":2927003000,"District":2927000000,"State":2900000000,"GEOJSON":[]},{"id":2927003014,"name":"Doodi Venkatapuram","level":3,"Mandal":2927003000,"District":2927000000,"State":2900000000,"GEOJSON":[]},{"id":2927003015,"name":"Lakshmakka Palle","level":3,"Mandal":2927003000,"District":2927000000,"State":2900000000,"GEOJSON":[]},{"id":2927003016,"name":"Kalvapally","level":3,"Mandal":2927003000,"District":2927000000,"State":2900000000,"GEOJSON":[]},{"id":2927003017,"name":"Challur","level":3,"Mandal":2927003000,"District":2927000000,"State":2900000000,"GEOJSON":[]},{"id":2927003018,"name":"Raghunadhapuram","level":3,"Mandal":2927003000,"District":2927000000,"State":2900000000,"GEOJSON":[]},{"id":2927003019,"name":"Begumpet","level":3,"Mandal":2927003000,"District":2927000000,"State":2900000000,"GEOJSON":[]}]