[{"id":2917005001,"name":"Chandrugonda","level":3,"Mandal":2917005000,"District":2917000000,"State":2900000000,"GEOJSON":[]},{"id":2917005002,"name":"Tippanapally","level":3,"Mandal":2917005000,"District":2917000000,"State":2900000000,"GEOJSON":[]},{"id":2917005003,"name":"Gurramgudem","level":3,"Mandal":2917005000,"District":2917000000,"State":2900000000,"GEOJSON":[]},{"id":2917005004,"name":"Sethaigudem","level":3,"Mandal":2917005000,"District":2917000000,"State":2900000000,"GEOJSON":[]},{"id":2917005005,"name":"Damarlacherla","level":3,"Mandal":2917005000,"District":2917000000,"State":2900000000,"GEOJSON":[]},{"id":2917005006,"name":"Maddukuru","level":3,"Mandal":2917005000,"District":2917000000,"State":2900000000,"GEOJSON":[]},{"id":2917005007,"name":"Pokalagudem","level":3,"Mandal":2917005000,"District":2917000000,"State":2900000000,"GEOJSON":[]},{"id":2917005008,"name":"Raikampadu","level":3,"Mandal":2917005000,"District":2917000000,"State":2900000000,"GEOJSON":[]},{"id":2917005009,"name":"Ganugapadu","level":3,"Mandal":2917005000,"District":2917000000,"State":2900000000,"GEOJSON":[]},{"id":2917005010,"name":"Tungaram","level":3,"Mandal":2917005000,"District":2917000000,"State":2900000000,"GEOJSON":[]}]