[{"id":2929010001,"name":"Quthbullapur","level":3,"Mandal":2929010000,"District":2929000000,"State":2900000000,"GEOJSON":[]},{"id":2929010002,"name":"Gajularamaram","level":3,"Mandal":2929010000,"District":2929000000,"State":2900000000,"GEOJSON":[]},{"id":2929010003,"name":"Suraram","level":3,"Mandal":2929010000,"District":2929000000,"State":2900000000,"GEOJSON":[]},{"id":2929010004,"name":"Pet Basheerabad","level":3,"Mandal":2929010000,"District":2929000000,"State":2900000000,"GEOJSON":[]},{"id":2929010005,"name":"Jeedimetla","level":3,"Mandal":2929010000,"District":2929000000,"State":2900000000,"GEOJSON":[]},{"id":2929010006,"name":"Namdarnagar","level":3,"Mandal":2929010000,"District":2929000000,"State":2900000000,"GEOJSON":[]}]